py_oathtool/__init__.py
py_oathtool/otp.py
py_oathtool-1.1.0.dist-info/METADATA
py_oathtool-1.1.0.dist-info/WHEEL
py_oathtool-1.1.0.dist-info/entry_points.txt
py_oathtool-1.1.0.dist-info/top_level.txt
py_oathtool-1.1.0.dist-info/RECORD
