Metadata-Version: 2.1
Name: py-oathtool
Version: 1.1.0
Summary: A python wrapper around oathtool
Home-page: https://github.com/matalo33/py_oathtool
Author: Matthew Taylor
Author-email: matthew@m-taylor.co.uk
License: GPLv2
Keywords: oathtool wrapper
Platform: UNKNOWN
Classifier: Development Status :: 4 - Beta
Classifier: Intended Audience :: Developers
Classifier: Intended Audience :: System Administrators
Classifier: Topic :: Security
Classifier: Topic :: System :: Systems Administration
Classifier: Topic :: Utilities
Classifier: License :: OSI Approved :: GNU General Public License v2 (GPLv2)
Classifier: Programming Language :: Python :: 3
Requires-Dist: subprocess32
Requires-Dist: pyaml
